powsolver/__init__.py
powsolver-0.1.7.dist-info/LICENSE
powsolver-0.1.7.dist-info/METADATA
powsolver-0.1.7.dist-info/WHEEL
powsolver-0.1.7.dist-info/top_level.txt
powsolver-0.1.7.dist-info/RECORD
