Metadata-Version: 2.1
Name: powsolver
Version: 0.1.7
Summary: Proof of Work solver mainly for CTF challenges
Home-page: http://github.com/apogiatzis/powsolver
Author: Antreas Pogiatzis
Author-email: pogiatzis.c.a@gmail.com
License: MIT
Platform: UNKNOWN
Classifier: Development Status :: 4 - Beta
Classifier: Intended Audience :: Developers
Classifier: Intended Audience :: Information Technology
Classifier: Topic :: Software Development :: Build Tools
Classifier: License :: OSI Approved :: MIT License
Classifier: Programming Language :: Python :: 3
Classifier: Programming Language :: Python :: 3.4
Classifier: Programming Language :: Python :: 3.5
Classifier: Programming Language :: Python :: 3.6
Classifier: Topic :: Security
Classifier: Topic :: Security :: Cryptography
Requires-Dist: dill (==0.3.2)
Requires-Dist: multiprocess (==0.70.10)
Requires-Dist: parse (==1.15.0)
Requires-Dist: pathos (==0.2.6)
Requires-Dist: pox (==0.2.8)
Requires-Dist: ppft (==1.6.6.2)
Requires-Dist: six (==1.15.0)
